README.md
setup.cfg
setup.py
avaland/__init__.py
avaland/config.py
avaland/data_types.py
avaland/download.py
avaland/exceptions.py
avaland/manager.py
avaland/music_base.py
avaland/search.py
avaland/utils.py
avaland.egg-info/PKG-INFO
avaland.egg-info/SOURCES.txt
avaland.egg-info/dependency_links.txt
avaland.egg-info/requires.txt
avaland.egg-info/top_level.txt
avaland/sources/__init__.py
avaland/sources/bia2.py
avaland/sources/navahang.py
avaland/sources/nex1music.py
avaland/sources/radiojavan.py
avaland/sources/rapfarsi.py
avaland/sources/wikiseda.py
bin/avaland
test/__init__.py
test/test_sources.py