Metadata-Version: 2.1
Name: avaland
Version: 0.0.1
Summary: Avaland is a music downloader to download music from many sources.
Home-page: https://github.com/Dragon-Born/avaland
Author: Arian Amiramjadi
Author-email: me@arian.lol
License: MIT
Download-URL: https://github.com/Dragon-Born/avaland/archive/v0.1.tar.gz
Keywords: Avaland,Persian music,Persian music downloader,Persian music api,Iranian music,Iranian music downloader,Iranian music api
Platform: UNKNOWN
Classifier: Development Status :: 3 - Alpha
Classifier: Intended Audience :: Developers
Classifier: Environment :: Console
Classifier: Topic :: Software Development :: Build Tools
Classifier: License :: OSI Approved :: MIT License
Classifier: Programming Language :: Python :: 3.5
Classifier: Programming Language :: Python :: 3.6
Classifier: Programming Language :: Python :: 3.7
Classifier: Programming Language :: Python :: 3.8
